llmescache/__init__.py
llmescache/langchain/__init__.py
llmescache/langchain/base.py
llmescache/langchain/cache.py
llmescache/langchain/storage.py
llmescache/py.typed
llm_elasticsearch_cache-0.2.6.dist-info/LICENSE
llm_elasticsearch_cache-0.2.6.dist-info/METADATA
llm_elasticsearch_cache-0.2.6.dist-info/WHEEL
llm_elasticsearch_cache-0.2.6.dist-info/RECORD
