Metadata-Version: 2.1
Name: llm-elasticsearch-cache
Version: 0.2.6
Summary: [IMPORTANT: This library is now part of LangChain, follow its official documentation] A caching layer for LLMs that exploits Elasticsearch, fully compatible with LangChain caching, both for chat and embeddings models.
Home-page: https://github.com/SpazioDati/llm-elasticsearch-cache
License: MIT
Keywords: langchain,elasticsearch,openai,llm,chatgpt
Author: SpazioDati s.r.l.
Maintainer: Giacomo Berardi
Maintainer-email: berardi@spaziodati.eu
Requires-Python: >=3.10,<4.0
Classifier: Development Status :: 7 - Inactive
Classifier: Intended Audience :: Developers
Classifier: Intended Audience :: Science/Research
Classifier: License :: OSI Approved :: MIT License
Classifier: Operating System :: OS Independent
Classifier: Programming Language :: Python :: 3
Classifier: Programming Language :: Python :: 3.10
Classifier: Programming Language :: Python :: 3.11
Classifier: Programming Language :: Python :: 3.12
Classifier: Topic :: Scientific/Engineering
Classifier: Topic :: Software Development
Requires-Dist: elasticsearch (>6)
Requires-Dist: langchain (>=0.1,<0.2)
Project-URL: Repository, https://github.com/SpazioDati/llm-elasticsearch-cache
